[
    {
        "word": "Vacancy",
        "type": [
            " [\/ve\u026a.k\u0259nt.si\/]"
        ],
        "definition": [
            "Bo\u02bbsh Ish O\u02bbrni"
        ]
    },
    {
        "word": "Vacant",
        "type": [
            " [\/ve\u026a.k\u0259nt\/]"
        ],
        "definition": [
            "Bo\u02bbsh"
        ]
    },
    {
        "word": "Vacate",
        "type": [
            " [\/v\u0259ke\u026at]"
        ],
        "definition": [
            "Bo\u02bbshatmoq"
        ]
    },
    {
        "word": "Vacation",
        "type": [
            " [\/ve\u026ake\u026a.\u0283\u0259n\/]"
        ],
        "definition": [
            "Tatil"
        ]
    },
    {
        "word": "Vaccinate",
        "type": [
            " [\/v\u00e6k.s\u026a.ne\u026at\/]"
        ],
        "definition": [
            "Emlamoq"
        ]
    },
    {
        "word": "Vaccine",
        "type": [
            " [\/v\u00e6k.si:n\/]"
        ],
        "definition": [
            "Vaksina"
        ]
    },
    {
        "word": "Vacuum",
        "type": [
            " [\/v\u00e6k.ju:m\/]"
        ],
        "definition": [
            "Vakum"
        ]
    },
    {
        "word": "Vagabond",
        "type": [
            " [\/v\u00e6g.\u0259.b\u0252nd\/]"
        ],
        "definition": [
            "Daydi"
        ]
    },
    {
        "word": "Vagina",
        "type": [
            " [\/v\u0259d\u0292a\u026a.n\u0259\/]"
        ],
        "definition": [
            "Qin"
        ]
    },
    {
        "word": "Vague",
        "type": [
            " [\/ve\u026ag\/]"
        ],
        "definition": [
            "Noaniq"
        ]
    },
    {
        "word": "Vain",
        "type": [
            " [\/ve\u026an\/]"
        ],
        "definition": [
            "Foydasiz"
        ]
    },
    {
        "word": "Vale",
        "type": [
            " [\/ve\u026al\/]"
        ],
        "definition": [
            "Vodiy"
        ]
    },
    {
        "word": "Valediction",
        "type": [
            " [\/v\u00e6l.\u0259d\u026ak.\u0283\u0259n\/]"
        ],
        "definition": [
            "Xayrlashish"
        ]
    },
    {
        "word": "Valet",
        "type": [
            " [\/v\u00e6l.e\u026a\/]"
        ],
        "definition": [
            "Xizmatkor"
        ]
    },
    {
        "word": "Valiant",
        "type": [
            " [\/v\u00e6l.i.\u0259nt\/]"
        ],
        "definition": [
            "Jasur"
        ]
    },
    {
        "word": "Valid",
        "type": [
            " [\/v\u00e6l.\u026ad\/]"
        ],
        "definition": [
            "Ishonchli"
        ]
    },
    {
        "word": "Validate",
        "type": [
            " [\/v\u00e6l.\u026a.de\u026at\/]"
        ],
        "definition": [
            "Tasdiqlamoq"
        ]
    },
    {
        "word": "Validity",
        "type": [
            " [\/v\u0259l\u026ad.\u026a.ti\/]"
        ],
        "definition": [
            "Qonuniylik"
        ]
    },
    {
        "word": "Valise",
        "type": [
            " [\/veli:z\/]"
        ],
        "definition": [
            "Chamadon"
        ]
    },
    {
        "word": "Valley",
        "type": [
            " [\/v\u00e6l.i\/]"
        ],
        "definition": [
            "Vodiy"
        ]
    },
    {
        "word": "Valuable",
        "type": [
            " [\/v\u00e6l.j\u028a.bl\u2006\u0329\/]"
        ],
        "definition": [
            "Qimmatli"
        ]
    },
    {
        "word": "Valuation",
        "type": [
            " [\/v\u00e6l.jue\u026a.\u0283\u0259n\/]"
        ],
        "definition": [
            "Baholash"
        ]
    },
    {
        "word": "Value",
        "type": [
            " [\/v\u00e6l.ju:\/]"
        ],
        "definition": [
            "Qiymat"
        ]
    },
    {
        "word": "Valve",
        "type": [
            " [\/v\u00e6lv\/]"
        ],
        "definition": [
            "Klapan"
        ]
    },
    {
        "word": "Vampire",
        "type": [
            " [\/v\u00e6m.pa\u026a\u0259r\/]"
        ],
        "definition": [
            "Vampir"
        ]
    },
    {
        "word": "Van",
        "type": [
            " [\/v\u00e6n\/]"
        ],
        "definition": [
            "Furgon"
        ]
    },
    {
        "word": "Vandal",
        "type": [
            " [\/v\u00e6n.d\u0259l\/]"
        ],
        "definition": [
            "Bezori"
        ]
    },
    {
        "word": "Vanguard",
        "type": [
            " [\/\u00f0\u0259v\u00e6\u014b.g\u0251:d\/]"
        ],
        "definition": [
            "Otryad"
        ]
    },
    {
        "word": "Vanilla",
        "type": [
            " [\/v\u0259n\u026al.\u0259\/]"
        ],
        "definition": [
            "Vanilin"
        ]
    },
    {
        "word": "Vanish",
        "type": [
            " [\/v\u00e6n.\u026a\u0283\/]"
        ],
        "definition": [
            "G\u02bboyib Bo\u02bblmoq"
        ]
    },
    {
        "word": "Vanity",
        "type": [
            " [\/v\u00e6n.\u026a.ti\/]"
        ],
        "definition": [
            "Manmanlik"
        ]
    },
    {
        "word": "Vanquish",
        "type": [
            " [\/v\u00e6\u014b.kw\u026a\u0283\/]"
        ],
        "definition": [
            "Yengmoq"
        ]
    },
    {
        "word": "Vaporize",
        "type": [
            " [\/ve\u026a.p\u0259r.a\u026az\/]"
        ],
        "definition": [
            "Bug\u02bblanmoq"
        ]
    },
    {
        "word": "Vapour",
        "type": [
            " [\/ve\u026a.p\u0259r\/]"
        ],
        "definition": [
            "Bug\u02bb"
        ]
    },
    {
        "word": "Variable",
        "type": [
            " [\/ve\u0259.ri.\u0259.bl\u2006\u0329\/]"
        ],
        "definition": [
            "O\u02bbzgaruvchi"
        ]
    },
    {
        "word": "Variant",
        "type": [
            " [\/ve\u0259.ri.\u0259nt\/]"
        ],
        "definition": [
            "Variant"
        ]
    },
    {
        "word": "Variation",
        "type": [
            " [\/ve\u0259.rie\u026a.\u0283\u0259n\/]"
        ],
        "definition": [
            "O\u02bbzgarish"
        ]
    },
    {
        "word": "Varied",
        "type": [
            " [\/ve\u0259.r\u026ad\/]"
        ],
        "definition": [
            "Turli"
        ]
    },
    {
        "word": "Variety",
        "type": [
            " [\/v\u0259ra\u026a\u0259.ti\/]"
        ],
        "definition": [
            "Har Xillik"
        ]
    },
    {
        "word": "Various",
        "type": [
            " [\/ve\u0259.ri.\u0259s\/]"
        ],
        "definition": [
            "Turli Xil"
        ]
    },
    {
        "word": "Varnish",
        "type": [
            " [\/v\u0251:.n\u026a\u0283\/]"
        ],
        "definition": [
            "Lok"
        ]
    },
    {
        "word": "Vary",
        "type": [
            " [\/ve\u0259.ri\/]"
        ],
        "definition": [
            "Farq Qilmoq"
        ]
    },
    {
        "word": "Vase",
        "type": [
            " [\/v\u0251:z\/]"
        ],
        "definition": [
            "Vaza"
        ]
    },
    {
        "word": "Vast",
        "type": [
            " [\/v\u0251:st\/]"
        ],
        "definition": [
            "Juda Katta"
        ]
    },
    {
        "word": "Vat",
        "type": [
            " [\/v\u00e6t\/]"
        ],
        "definition": [
            "Bak"
        ]
    },
    {
        "word": "Vault",
        "type": [
            " [\/v\u0252lt\/]"
        ],
        "definition": [
            "Gumbaz"
        ]
    },
    {
        "word": "Veal",
        "type": [
            " [\/vi:l\/]"
        ],
        "definition": [
            "Buzoq Go\u02bbshti"
        ]
    },
    {
        "word": "Vector",
        "type": [
            " [\/vek.t\u0259r\/]"
        ],
        "definition": [
            "Vektor"
        ]
    },
    {
        "word": "Veer",
        "type": [
            " [\/v\u026a\u0259r\/]"
        ],
        "definition": [
            "Yo\u02bbnalishni O\u02bbzgartirmoq"
        ]
    },
    {
        "word": "Vegetable",
        "type": [
            " [\/ved\u0292.t\u0259.bl\u2006\u0329\/]"
        ],
        "definition": [
            "Sabzavot"
        ]
    },
    {
        "word": "Vegetarian",
        "type": [
            " [\/ved\u0292.\u026ate\u0259.ri.\u0259n\/]"
        ],
        "definition": [
            "Vegetarian"
        ]
    },
    {
        "word": "Vegetation",
        "type": [
            " [\/ved\u0292.\u026ate\u026a.\u0283\u0259n\/]"
        ],
        "definition": [
            "O\u02bbsimliklar"
        ]
    },
    {
        "word": "Vehemence",
        "type": [
            " [\/vi:.\u0259.m\u0259nts\/]"
        ],
        "definition": [
            "Kuch"
        ]
    },
    {
        "word": "Vehement",
        "type": [
            " [\/vi.\u0259.m\u0259nt\/]"
        ],
        "definition": [
            "Kuchli"
        ]
    },
    {
        "word": "Vehicle",
        "type": [
            " [\/vi:.\u026a.kl\u2006\u0329\/]"
        ],
        "definition": [
            "Transport"
        ]
    },
    {
        "word": "Veil",
        "type": [
            " [\/ve\u026al\/]"
        ],
        "definition": [
            "Yuzga Tutiluvchi Gazlama"
        ]
    },
    {
        "word": "Vein",
        "type": [
            " [\/ve\u026an\/]"
        ],
        "definition": [
            "Vena"
        ]
    },
    {
        "word": "Velocity",
        "type": [
            " [\/v\u0259l\u0252s.\u026a.ti\/]"
        ],
        "definition": [
            "Tezlik"
        ]
    },
    {
        "word": "Velvet",
        "type": [
            " [\/vel.v\u026at\/]"
        ],
        "definition": [
            "Baxmal"
        ]
    },
    {
        "word": "Velvety",
        "type": [
            " [\/vel.v\u026at\/]"
        ],
        "definition": [
            "Mayin"
        ]
    },
    {
        "word": "Venal",
        "type": [
            " [\/vi:.n\u0259l\/]"
        ],
        "definition": [
            "Sotqin"
        ]
    },
    {
        "word": "Vend",
        "type": [
            " [\/ven.d\/]"
        ],
        "definition": [
            "Sotmoq"
        ]
    },
    {
        "word": "Vendetta",
        "type": [
            " [\/vendet.\u0259\/]"
        ],
        "definition": [
            "Qasos"
        ]
    },
    {
        "word": "Vendor",
        "type": [
            " [\/ven.d\u0259r\/]"
        ],
        "definition": [
            "Sotuvchi"
        ]
    },
    {
        "word": "Veneer",
        "type": [
            " [\/v\u0259n\u026a\u0259r\/]"
        ],
        "definition": [
            "Fanera"
        ]
    },
    {
        "word": "Venerable",
        "type": [
            " [\/ven.\u0259r.\u0259.bl\/]"
        ],
        "definition": [
            "Hurmatli"
        ]
    },
    {
        "word": "Venerate",
        "type": [
            " [\/ven.\u0259r.e\u026at\/]"
        ],
        "definition": [
            "Hurmat Qilmoq"
        ]
    },
    {
        "word": "Veneration",
        "type": [
            " [\/ven.\u0259re\u026a.\u0283\u0259n\/]"
        ],
        "definition": [
            "Qattiq Hurmat"
        ]
    },
    {
        "word": "Vengeance",
        "type": [
            " [\/ven.d\u0292\u0259nts\/]"
        ],
        "definition": [
            "Qasos"
        ]
    },
    {
        "word": "Venison",
        "type": [
            " [\/ven.\u026a.s\u0259n\/]"
        ],
        "definition": [
            "Bug\u02bbu Go\u02bbshti"
        ]
    },
    {
        "word": "Venom",
        "type": [
            " [\/ven\u0259m\/]"
        ],
        "definition": [
            "Zahar"
        ]
    },
    {
        "word": "Vent",
        "type": [
            " [\/vent\/]"
        ],
        "definition": [
            "Shamollatish"
        ]
    },
    {
        "word": "Ventilate",
        "type": [
            " [\/ven.t\u026a.le\u026at\/]"
        ],
        "definition": [
            "Havosini Yangilamoq"
        ]
    },
    {
        "word": "Ventilation",
        "type": [
            " [\/ven.t\u026ale\u026a.\u0283\u0259n\/]"
        ],
        "definition": [
            "Havosini Yangilash"
        ]
    },
    {
        "word": "Ventilator",
        "type": [
            " [\/ven.t\u026a.le\u026a.t\u0259r\/]"
        ],
        "definition": [
            "Ventilyator"
        ]
    },
    {
        "word": "Ventricle",
        "type": [
            " [\/ven.tr\u026a.kl\u2006\u0329\/]"
        ],
        "definition": [
            "Yurak Qorinchasi"
        ]
    },
    {
        "word": "Ventriloquism",
        "type": [
            " [\/ventr\u026al.\u0259.kw\u026a.z\u0259m\/]"
        ],
        "definition": [
            "Og\u02bbizni Qimirlatmay Gapirish"
        ]
    },
    {
        "word": "Ventriloquist",
        "type": [
            " [\/ventr\u026al.\u0259.kw\u026ast\/]"
        ],
        "definition": [
            "Labini Qimirlatmay Gapira Oladigan Odam"
        ]
    },
    {
        "word": "Venture",
        "type": [
            " [\/ven.t\u0283\u0259r\/]"
        ],
        "definition": [
            "Tavakkal Ish"
        ]
    },
    {
        "word": "Venturesome",
        "type": [
            " [\/ven.t\u0283\u0259.s\u0259m\/]"
        ],
        "definition": [
            "Tavakkalchi"
        ]
    },
    {
        "word": "Venue",
        "type": [
            " [\/ven.ju:\/]"
        ],
        "definition": [
            "Yig\u02bbilish Joyi"
        ]
    },
    {
        "word": "Veranda",
        "type": [
            " [\/v\u0259r\u00e6n.d\u0259\/]"
        ],
        "definition": [
            "Ayvon"
        ]
    },
    {
        "word": "Verb",
        "type": [
            " [\/v\u025c:b\/]"
        ],
        "definition": [
            "Fel"
        ]
    },
    {
        "word": "Verbal",
        "type": [
            " [\/v\u025c:.b\u0259l\/]"
        ],
        "definition": [
            "Og\u02bbzaki"
        ]
    },
    {
        "word": "Verbose",
        "type": [
            " [\/v\u025c:b\u0259\u028as\/]"
        ],
        "definition": [
            "Ezma"
        ]
    },
    {
        "word": "Verdict",
        "type": [
            " [\/v\u025c:.d\u026akt\/]"
        ],
        "definition": [
            "Hukm"
        ]
    },
    {
        "word": "Verge",
        "type": [
            " [\/v\u025c:d\u0292\/]"
        ],
        "definition": [
            "Chegara"
        ]
    },
    {
        "word": "Verification",
        "type": [
            " [\/ver.\u026a.f\u026ake\u026a.\u0283\u0259n\/]"
        ],
        "definition": [
            "Tekshirish"
        ]
    },
    {
        "word": "Verify",
        "type": [
            " [\/ver.\u026a.fa\u026a\/]"
        ],
        "definition": [
            "Tasdiqlamoq"
        ]
    },
    {
        "word": "Veritable",
        "type": [
            " [\/ver.\u026a.t\u0259.bl\u2006\u0329\/]"
        ],
        "definition": [
            "Haqiqiy"
        ]
    },
    {
        "word": "Vermicelli",
        "type": [
            " [\/v\u025c:.m\u026at\u0283el.i\/]"
        ],
        "definition": [
            "Vermishel"
        ]
    },
    {
        "word": "Vermin",
        "type": [
            " [\/v\u025c:.m\u026an\/]"
        ],
        "definition": [
            "Parazitlar"
        ]
    },
    {
        "word": "Vernacular",
        "type": [
            " [\/v\u0259n\u00e6k.j\u028a.l\u0259r\/]"
        ],
        "definition": [
            "Ona Tili"
        ]
    },
    {
        "word": "Versatile",
        "type": [
            " [\/v\u025c.s\u0259.ta\u026al\/]"
        ],
        "definition": [
            "Ko\u02bbp Qirrali"
        ]
    },
    {
        "word": "Verse",
        "type": [
            " [\/v\u025c:s\/]"
        ],
        "definition": [
            "Misra"
        ]
    },
    {
        "word": "Version",
        "type": [
            " [\/v\u025c:.\u0283\u0259n\/]"
        ],
        "definition": [
            "Boshqa Ko\u02bbrinish"
        ]
    },
    {
        "word": "Versus",
        "type": [
            " [\/v\u025c:.s\u0259s\/]"
        ],
        "definition": [
            "Qarshi"
        ]
    },
    {
        "word": "Vertebra",
        "type": [
            " [\/v\u025c:.t\u026a.br\u0259\/]"
        ],
        "definition": [
            "Umurtqa Suyagi"
        ]
    },
    {
        "word": "Vertebrate",
        "type": [
            " [\/v\u025c:.t\u026a.br\u0259t\/]"
        ],
        "definition": [
            "Umurtqali"
        ]
    },
    {
        "word": "Vertical",
        "type": [
            " [\/v\u025c:.t\u026a.k\u0259l\/]"
        ],
        "definition": [
            "Tik"
        ]
    },
    {
        "word": "Vertigo",
        "type": [
            " [\/v\u025c:.t\u026a.g\u0259\u028a\/]"
        ],
        "definition": [
            "Bosh Aylanishi"
        ]
    },
    {
        "word": "Very",
        "type": [
            " [\/ver.i\/]"
        ],
        "definition": [
            "Juda"
        ]
    },
    {
        "word": "Vessel",
        "type": [
            " [\/ves.\u0259l\/]"
        ],
        "definition": [
            "Kema"
        ]
    },
    {
        "word": "Vest",
        "type": [
            " [\/vest\/]"
        ],
        "definition": [
            "Mayka"
        ]
    },
    {
        "word": "Vestibule",
        "type": [
            " [\/ves.t\u026a.bju:l\/]"
        ],
        "definition": [
            "Dahliz"
        ]
    },
    {
        "word": "Vestige",
        "type": [
            " [\/ves.t\u026ad\u0292\/]"
        ],
        "definition": [
            "Qolgan Nishon"
        ]
    },
    {
        "word": "Vestment",
        "type": [
            " [\/vest.m\u0259nts\/]"
        ],
        "definition": [
            "Sarpo"
        ]
    },
    {
        "word": "Vet",
        "type": [
            " [\/vet\/]"
        ],
        "definition": [
            "Veterinar"
        ]
    },
    {
        "word": "Veteran",
        "type": [
            " [\/vet.\u0259r.\u0259n\/]"
        ],
        "definition": [
            "Veteran"
        ]
    },
    {
        "word": "Veterinary",
        "type": [
            " [\/vet.\u0259r.\u026a.n\u0259r.i\/]"
        ],
        "definition": [
            "Veterinariya"
        ]
    },
    {
        "word": "Veto",
        "type": [
            " [\/vi:.t\u0259\u028a\/]"
        ],
        "definition": [
            "Man Qilish"
        ]
    },
    {
        "word": "Vex",
        "type": [
            " [\/veks\/]"
        ],
        "definition": [
            "Xafa Qilmoq"
        ]
    },
    {
        "word": "Vexatious",
        "type": [
            " [\/vekse\u026a.\u0283\u0259s\/]"
        ],
        "definition": [
            "Xafa Qiladigan"
        ]
    },
    {
        "word": "Via",
        "type": [
            " [\/va\u026a\u0259\/]"
        ],
        "definition": [
            "Orqali"
        ]
    },
    {
        "word": "Viable",
        "type": [
            " [\/va\u026a.\u0259.bl\u2006\u0329\/]"
        ],
        "definition": [
            "Rivojlana Oladigan"
        ]
    },
    {
        "word": "Viaduct",
        "type": [
            " [\/va\u026a\u0259.d\u028ckt\/]"
        ],
        "definition": [
            "Ko\u02bbprik"
        ]
    },
    {
        "word": "Vibrant",
        "type": [
            " [\/va\u026a.br\u0259nt\/]"
        ],
        "definition": [
            "Tebranadigan"
        ]
    },
    {
        "word": "Vibrate",
        "type": [
            " [\/va\u026abre\u026at\/]"
        ],
        "definition": [
            "Tebranmoq"
        ]
    },
    {
        "word": "Vibration",
        "type": [
            " [\/va\u026abre\u026a.\u0283\u0259n\/]"
        ],
        "definition": [
            "Tebranish"
        ]
    },
    {
        "word": "Vicar",
        "type": [
            " [\/v\u026ak.\u0259r\/]"
        ],
        "definition": [
            "Ruhoniy"
        ]
    },
    {
        "word": "Vice",
        "type": [
            " [\/va\u026as\/]"
        ],
        "definition": [
            "Nuqson"
        ]
    },
    {
        "word": "Vice Versa",
        "type": [
            " [\/va\u026asv\u025c:.s\u0259\/]"
        ],
        "definition": [
            "Teskarisiga"
        ]
    },
    {
        "word": "Vicinity",
        "type": [
            " [\/v\u026as\u026an.\u026a.ti\/]"
        ],
        "definition": [
            "Qo\u02bbshnilik"
        ]
    },
    {
        "word": "Vicious",
        "type": [
            " [\/v\u026a\u0283.\u0259s\/]"
        ],
        "definition": [
            "Ahloqsiz"
        ]
    },
    {
        "word": "Vicious Circle",
        "type": [
            " [\/v\u026a\u0283.\u0259s.s\u025c:.kl\/]"
        ],
        "definition": [
            "Og\u02bbir Ahvol"
        ]
    },
    {
        "word": "Victim",
        "type": [
            " [\/v\u026ak.t\u026am\/]"
        ],
        "definition": [
            "Qurbon"
        ]
    },
    {
        "word": "Victimize",
        "type": [
            " [\/v\u026ak.t\u026a.ma\u026az\/]"
        ],
        "definition": [
            "Qiynamoq"
        ]
    },
    {
        "word": "Victor",
        "type": [
            " [\/v\u026ak.t\u0259r\/]"
        ],
        "definition": [
            "G\u02bbolib"
        ]
    },
    {
        "word": "Victorious",
        "type": [
            " [\/v\u026akt\u0254:.ri.\u0259s\/]"
        ],
        "definition": [
            "G\u02bbolibona"
        ]
    },
    {
        "word": "Victory",
        "type": [
            " [\/v\u026ak.t\u0259r.i\/]"
        ],
        "definition": [
            "G\u02bbalaba"
        ]
    },
    {
        "word": "Video",
        "type": [
            " [\/v\u026ad.i.\u0259\u028a\/]"
        ],
        "definition": [
            "Video"
        ]
    },
    {
        "word": "View",
        "type": [
            " [\/vju:\/]"
        ],
        "definition": [
            "Qarash"
        ]
    },
    {
        "word": "Viewer",
        "type": [
            " [\/vju:.\u0259r\/]"
        ],
        "definition": [
            "Kuzatuvchi"
        ]
    },
    {
        "word": "Vigil",
        "type": [
            " [\/v\u026ad\u0292.\u026al\/]"
        ],
        "definition": [
            "Bedorlik"
        ]
    },
    {
        "word": "Vigilant",
        "type": [
            " [\/v\u026ad\u0292.\u026a.l\u0259nt\/]"
        ],
        "definition": [
            "Hushyor"
        ]
    },
    {
        "word": "Vigorous",
        "type": [
            " [\/v\u026ag.\u0259r.\u0259s\/]"
        ],
        "definition": [
            "Harakatchan"
        ]
    },
    {
        "word": "Vigour",
        "type": [
            " [\/v\u026ag.\u0259r\/]"
        ],
        "definition": [
            "G\u02bbayrat"
        ]
    },
    {
        "word": "Vile",
        "type": [
            " [\/va\u026al\/]"
        ],
        "definition": [
            "Pastkash"
        ]
    },
    {
        "word": "Villa",
        "type": [
            " [\/v\u026al.\u0259\/]"
        ],
        "definition": [
            "Dala Hovli"
        ]
    },
    {
        "word": "Village",
        "type": [
            " [\/v\u026al.\u026ad\u0292\/]"
        ],
        "definition": [
            "Qishloq"
        ]
    },
    {
        "word": "Villager",
        "type": [
            " [\/v\u026al.\u026a.d\u0292\u0259r\/]"
        ],
        "definition": [
            "Qishloqlik"
        ]
    },
    {
        "word": "Villain",
        "type": [
            " [\/v\u026al.\u0259n\/]"
        ],
        "definition": [
            "Salbiy Qahramon"
        ]
    },
    {
        "word": "Vindicate",
        "type": [
            " [\/v\u026an.d\u026a.ke\u026at\/]"
        ],
        "definition": [
            "Isbotlamoq"
        ]
    },
    {
        "word": "Vindication",
        "type": [
            " [\/v\u026an.d\u026ake\u026a.\u0283\u0259n\/]"
        ],
        "definition": [
            "Isbotlash"
        ]
    },
    {
        "word": "Vindictive",
        "type": [
            " [\/v\u026and\u026ak.t\u026av\/]"
        ],
        "definition": [
            "Jazolashga Oid"
        ]
    },
    {
        "word": "Vine",
        "type": [
            " [\/va\u026an\/]"
        ],
        "definition": [
            "Tok Novdasi"
        ]
    },
    {
        "word": "Vinegar",
        "type": [
            " [\/v\u026an.\u026a.g\u0259r\/]"
        ],
        "definition": [
            "Sirka"
        ]
    },
    {
        "word": "Vineyard",
        "type": [
            " [\/v\u026an.j\u0251:d\/]"
        ],
        "definition": [
            "Uzumzor"
        ]
    },
    {
        "word": "Vintage",
        "type": [
            " [\/v\u026an.t\u026ad\u0292\/]"
        ],
        "definition": [
            "Yuqori Sifat"
        ]
    },
    {
        "word": "Viola",
        "type": [
            " [\/va\u026a\u0259\u028a.l\u0259\/]"
        ],
        "definition": [
            "Viola"
        ]
    },
    {
        "word": "Violate",
        "type": [
            " [\/va\u026a\u0259.le\u026at\/]"
        ],
        "definition": [
            "Buzmoq,"
        ]
    },
    {
        "word": "Violation",
        "type": [
            " [\/va\u026a\u0259le\u026a.\u0283\u0259n\/]"
        ],
        "definition": [
            "Buzish"
        ]
    },
    {
        "word": "Violence",
        "type": [
            " [\/va\u026a\u0259.l\u0259nts\/]"
        ],
        "definition": [
            "G\u02bbazab"
        ]
    },
    {
        "word": "Violent",
        "type": [
            " [\/va\u026a\u0259.l\u0259nt\/]"
        ],
        "definition": [
            "G\u02bbazabli"
        ]
    },
    {
        "word": "Violet",
        "type": [
            " [\/va\u026a\u0259.l\u0259t\/]"
        ],
        "definition": [
            "Binafsha"
        ]
    },
    {
        "word": "Violin",
        "type": [
            " [\/va\u026a\u0259l\u026an\/]"
        ],
        "definition": [
            "Skripka"
        ]
    },
    {
        "word": "Viper",
        "type": [
            " [\/va\u026a.p\u0259r\/]"
        ],
        "definition": [
            "Qora Ilon"
        ]
    },
    {
        "word": "Virgin",
        "type": [
            " [\/v\u025c:.d\u0292\u026an\/]"
        ],
        "definition": [
            "Bokira"
        ]
    },
    {
        "word": "Virginity",
        "type": [
            " [\/v\u0259d\u0292\u026an.\u026a.ti\/]"
        ],
        "definition": [
            "Bokiralik"
        ]
    },
    {
        "word": "Virile",
        "type": [
            " [\/v\u026ar.a\u026al\/]"
        ],
        "definition": [
            "Balog\u02bbatga Yetgan"
        ]
    },
    {
        "word": "Virtual",
        "type": [
            " [\/v\u025c:.tju.\u0259l\/]"
        ],
        "definition": [
            "Haqiqiy"
        ]
    },
    {
        "word": "Virtually",
        "type": [
            " [\/v\u025c:.tju.\u0259.li\/]"
        ],
        "definition": [
            "Aslida"
        ]
    },
    {
        "word": "Virtue",
        "type": [
            " [\/v\u025c:.tju:\/]"
        ],
        "definition": [
            "Yaxshilik"
        ]
    },
    {
        "word": "Virtuous",
        "type": [
            " [\/v\u025c:.tju.\u0259s\/]"
        ],
        "definition": [
            "Xayrli"
        ]
    },
    {
        "word": "Virus",
        "type": [
            " [\/va\u026a\u0259.r\u0259s\/]"
        ],
        "definition": [
            "Virus"
        ]
    },
    {
        "word": "Visa",
        "type": [
            " [\/vi:.z\u0259\/]"
        ],
        "definition": [
            "Viza"
        ]
    },
    {
        "word": "Viscount",
        "type": [
            " [\/va\u026a.ka\u028ant\/]"
        ],
        "definition": [
            "Vikont"
        ]
    },
    {
        "word": "Viscous",
        "type": [
            " [\/v\u026as.k\u0259s\/]"
        ],
        "definition": [
            "Yopishqoq"
        ]
    },
    {
        "word": "Visibility",
        "type": [
            " [\/v\u026az.\u026ab\u026al.\u026a.ti\/]"
        ],
        "definition": [
            "Ko\u02bbrinish"
        ]
    },
    {
        "word": "Visible",
        "type": [
            " [\/v\u026az.\u026a.bl\u2006\u0329\/]"
        ],
        "definition": [
            "Ko\u02bbrinadigan"
        ]
    },
    {
        "word": "Vision",
        "type": [
            " [\/v\u026a\u0292.\u0259n\/]"
        ],
        "definition": [
            "Ko\u02bbrinish"
        ]
    },
    {
        "word": "Visionary",
        "type": [
            " [\/v\u026a\u0292.\u0259n.ri\/]"
        ],
        "definition": [
            "Oldindan Ko\u02bbruvchi"
        ]
    },
    {
        "word": "Visit",
        "type": [
            " [\/v\u026az.\u026at\/]"
        ],
        "definition": [
            "Tashrif Buyurmoq"
        ]
    },
    {
        "word": "Visitor",
        "type": [
            " [\/v\u026az.\u026a.t\u0259r\/]"
        ],
        "definition": [
            "Tashrif Buyuruvchi"
        ]
    },
    {
        "word": "Visor",
        "type": [
            " [\/va\u026a.z\u0259r\/]"
        ],
        "definition": [
            "Kapishonka"
        ]
    },
    {
        "word": "Visual",
        "type": [
            " [\/v\u026a\u0292.u.\u0259l\/]"
        ],
        "definition": [
            "Ko\u02bbradigan"
        ]
    },
    {
        "word": "Visualize",
        "type": [
            " [\/v\u026a\u0292.u.\u0259l.a\u026az\/]"
        ],
        "definition": [
            "Tasavvur Qilmoq"
        ]
    },
    {
        "word": "Vital",
        "type": [
            " [\/va\u026a.t\u0259l\/]"
        ],
        "definition": [
            "Juda Muhim"
        ]
    },
    {
        "word": "Vitality",
        "type": [
            " [\/va\u026at\u00e6l.\u026a.ti\/]"
        ],
        "definition": [
            "Jo\u02bbshqinlik"
        ]
    },
    {
        "word": "Vitamin",
        "type": [
            " [\/v\u026at.\u0259.m\u026an\/]"
        ],
        "definition": [
            "Vitamin"
        ]
    },
    {
        "word": "Vitiate",
        "type": [
            " [\/v\u026a\u0283.i.e\u026at\/]"
        ],
        "definition": [
            "Buzmoq"
        ]
    },
    {
        "word": "Vitreous",
        "type": [
            " [\/v\u026at.ri.\u0259s\/]"
        ],
        "definition": [
            "Shishadek"
        ]
    },
    {
        "word": "Vivacious",
        "type": [
            " [\/v\u026ave\u026a.\u0283\u0259s\/]"
        ],
        "definition": [
            "Jonli"
        ]
    },
    {
        "word": "Vivid",
        "type": [
            " [\/v\u026av.\u026ad\/]"
        ],
        "definition": [
            "Yorqin"
        ]
    },
    {
        "word": "Vocabulary",
        "type": [
            " [\/v\u0259k\u00e6b.j\u028a.l\u0259r.i\/]"
        ],
        "definition": [
            "So\u02bbz Boyligi"
        ]
    },
    {
        "word": "Vocal",
        "type": [
            " [\/v\u0259\u028a.k\u0259l\/]"
        ],
        "definition": [
            "Ovozga Oid"
        ]
    },
    {
        "word": "Vocalist",
        "type": [
            " [\/v\u0259\u028a.k\u0259l.\u026ast\/]"
        ],
        "definition": [
            "Qo\u02bbshiqchi"
        ]
    },
    {
        "word": "Vocation",
        "type": [
            " [\/v\u0259\u028ake\u026a.\u0283\u0259n\/]"
        ],
        "definition": [
            "Mayl"
        ]
    },
    {
        "word": "Vocational",
        "type": [
            " [\/v\u0259\u028ake\u026a.\u0283\u0259n.\u0259l\/]"
        ],
        "definition": [
            "Kasbiy"
        ]
    },
    {
        "word": "Vodka",
        "type": [
            " [\/v\u0252d.k\u0259\/]"
        ],
        "definition": [
            "Aroq"
        ]
    },
    {
        "word": "Vogue",
        "type": [
            " [\/v\u0259\u028ag\/]"
        ],
        "definition": [
            "Moda"
        ]
    },
    {
        "word": "Voice",
        "type": [
            " [\/v\u0254\u026as\/]"
        ],
        "definition": [
            "Ovoz"
        ]
    },
    {
        "word": "Void",
        "type": [
            " [\/v\u0254\u026ad\/]"
        ],
        "definition": [
            "Bo\u02bbsh"
        ]
    },
    {
        "word": "Volatile",
        "type": [
            " [\/v\u0252l.\u0259.ta\u026al\/]"
        ],
        "definition": [
            "O\u02bbzgaruvchan"
        ]
    },
    {
        "word": "Volcanic",
        "type": [
            " [\/v\u0252lk\u00e6n.\u026ak\/]"
        ],
        "definition": [
            "Vulqonli"
        ]
    },
    {
        "word": "Volcano",
        "type": [
            " [\/v\u0252lke\u026a.n\u0259\u028a\/]"
        ],
        "definition": [
            "Vulqon"
        ]
    },
    {
        "word": "Volition",
        "type": [
            " [\/v\u0259l\u026a\u0283.\u0259n\/]"
        ],
        "definition": [
            "Istak"
        ]
    },
    {
        "word": "Volley",
        "type": [
            " [\/v\u0252l.i\/]"
        ],
        "definition": [
            "O\u02bbq Otish"
        ]
    },
    {
        "word": "Volleyball",
        "type": [
            " [\/v\u0252l.i.b\u0254:l\/]"
        ],
        "definition": [
            "Voleybol"
        ]
    },
    {
        "word": "Volt",
        "type": [
            " [\/v\u0252lt\/]"
        ],
        "definition": [
            "Volt"
        ]
    },
    {
        "word": "Voltage",
        "type": [
            " [\/v\u0252l.t\u026ad\u0292\/]"
        ],
        "definition": [
            "Voltaj"
        ]
    },
    {
        "word": "Volume",
        "type": [
            " [\/v\u0252l.ju:m\/]"
        ],
        "definition": [
            "Hajm"
        ]
    },
    {
        "word": "Voluntary",
        "type": [
            " [\/v\u0252l.\u0259n.tri\/]"
        ],
        "definition": [
            "Ixtiyoriy"
        ]
    },
    {
        "word": "Volunteer",
        "type": [
            " [\/v\u0252l.\u0259nt\u026a\u0259r\/]"
        ],
        "definition": [
            "Talabgor"
        ]
    },
    {
        "word": "Vomit",
        "type": [
            " [\/v\u0252m.\u026at\/]"
        ],
        "definition": [
            "Qusmoq"
        ]
    },
    {
        "word": "Voracious",
        "type": [
            " [\/v\u0259re\u026a.\u0283\u0259s\/]"
        ],
        "definition": [
            "Ochko\u02bbz"
        ]
    },
    {
        "word": "Vote",
        "type": [
            " [\/v\u0259\u028at\/]"
        ],
        "definition": [
            "Ovoz Bermoq"
        ]
    },
    {
        "word": "Voter",
        "type": [
            " [\/v\u0259\u028a.t\u0259r\/]"
        ],
        "definition": [
            "Saylovchi"
        ]
    },
    {
        "word": "Vouch",
        "type": [
            " [\/va\u028at\u0283\/]"
        ],
        "definition": [
            "Kafolat Bermoq"
        ]
    },
    {
        "word": "Voucher",
        "type": [
            " [\/va\u028a.t\u0283\u0259r\/]"
        ],
        "definition": [
            "Kafolat Xati"
        ]
    },
    {
        "word": "Vouchsafe",
        "type": [
            " [\/va\u028at\u0283se\u026af\/]"
        ],
        "definition": [
            "Munosib Ko\u02bbrmoq"
        ]
    },
    {
        "word": "Vow",
        "type": [
            " [\/va\u028a\/]"
        ],
        "definition": [
            "Qasam Ichmoq"
        ]
    },
    {
        "word": "Vowel",
        "type": [
            " [\/va\u028a\u0259l\/]"
        ],
        "definition": [
            "Unli Tovush"
        ]
    },
    {
        "word": "Voyage",
        "type": [
            " [\/v\u0254\u026a.\u026ad\u0292\/]"
        ],
        "definition": [
            "Dengiz Sayohati"
        ]
    },
    {
        "word": "Voyager",
        "type": [
            " [\/v\u0254\u026a.\u026a.d\u0292\u0259r\/]"
        ],
        "definition": [
            "Sayohatchi"
        ]
    },
    {
        "word": "Vulgar",
        "type": [
            " [\/v\u028cl.g\u0259r\/]"
        ],
        "definition": [
            "Qo\u02bbpol"
        ]
    },
    {
        "word": "Vulnerable",
        "type": [
            " [\/v\u028cl.n\u0259r.\u0259.bl\u2006\u0329\/]"
        ],
        "definition": [
            "Ko\u02bbngli Nozik"
        ]
    },
    {
        "word": "Vulture",
        "type": [
            " [\/v\u028cl.t\u0283\u0259r\/]"
        ],
        "definition": [
            "Kalxat"
        ]
    },
    {
        "word": "Vulva",
        "type": [
            " [\/v\u028cl.v\u0259\/]"
        ],
        "definition": [
            "Jinsiy Azo"
        ]
    }
]