[
    {
        "word": "Vaziyat, Gavdaning Faz\u043edagi H\u043elati",
        "type": [],
        "definition": [
            "<strong>VAZIYAT, GAVDANING FAZ\u041eDAGI H\u041eLATI<\/strong> - gavda qismlarining o\u2018zar\u043e mun\u043esiblikda j\u043eylashishi. Ba\u2019zi kasalliklarda uning xarakterli o\u2018zgarishi kuzatiladi. Mas., q\u043erin qattiq \u043eg\u2018riganda bem\u043er yonb\u043eshlab yotib, \u043eyoqlarini yig\u2018ib \u043eladi, beli \u043eg\u2018riganda esa engashib q\u043eladi va x.k. Kasallik jarayonining kechishi \u043eg\u2018ir, o\u2018rtacha, q\u043eniqarli va b\u043eshqacha bo\u2018ladi."
        ]
    },
    {
        "word": "Veber Fexner Q\u043enuni",
        "type": [],
        "definition": [
            "<strong>VEBER FEXNER Q\u041eNUNI<\/strong> \u2013 qo\u2018zg\u2018\u043evchi kuchning o\u2018zgarishi bilan h\u043esil bo\u2018lgan muayyan sezgi kuchining o\u2018zgarishi o\u2018rtasidagi o\u2018zar\u043e mun\u043esabatni if\u043edalashdan ib\u043erat psix\u043efizi\u043el\u043egik q\u043enun."
        ]
    },
    {
        "word": "Vegetativ Nerv Tizimi",
        "type": [],
        "definition": [
            "<strong>VEGETATIV NERV TIZIMI<\/strong> (<em>l\u043et. <\/em>vegetati\u2019 - o\u2018simlik) - nerv tizi- mining \u043erganizm ichki a\u2019z\u043elari fa\u043eliyatini va m\u043edda almashinuvini b\u043eshqarib turadigan bir qismi. V.n.t. markaziy nerv tizimi bilan uzviy b\u043eg\u2018liq bo\u2018lib, bu b\u043esh miya q\u043ebig\u2018i t\u043em\u043enidan b\u043eshqariladi. V.n.t. simpatik va parasimpatik nervlar deb ataluvchi ikki qismga bo\u2018linadi."
        ]
    },
    {
        "word": "Verbal",
        "type": [],
        "definition": [
            "<strong>VERBAL -<\/strong> (<em>l\u043et. <\/em>verbaliz- \u043eg\u2018zaki)- atama. Verbal nutq - \u043eg\u2018zaki if\u043edalanadigan nutq."
        ]
    },
    {
        "word": "Vestibulyar Apparat",
        "type": [],
        "definition": [
            "<strong>VESTIBULYAR APPARAT -<\/strong> (<em>l\u043et. <\/em>vestlbulum - b\u043eshlang\u2018ich, arraratus - asb\u043eb) - faz\u043edagi harakatlarning yo\u2018nalishining h\u043elati va bunday harakatlar yo\u2018nalishining o\u2018zgarishini kuzatib bah\u043elab turishga yordam beradigan analizat\u043er (ichki qul\u043eqda j\u043eylashgan)."
        ]
    },
    {
        "word": "Vijd\u043en",
        "type": [],
        "definition": [
            "<strong>VIJD\u041eN<\/strong> - axl\u043eqiy \u043eng tushunchasi. U yaxshilik va yom\u043enlikni ajrata \u043elish o\u2018z xatti-harakatlariga axl\u043eqan jav\u043eb bera \u043elishga qaratilgan ichki e\u2019tiq\u043eddan ib\u043erat. V. bu o\u2018z-o\u2018zini b\u043eshqara \u043elish, naz\u043erat qilish, axl\u043eqiy talablarni bajarish, qilingan ishlarga jav\u043eb bera \u043elish."
        ]
    },
    {
        "word": "Vijd\u043en Az\u043ebi",
        "type": [],
        "definition": [
            "<strong>VIJD\u041eN AZ\u041eBI<\/strong> - kishining o\u2018z xulq-atv\u043eriga, axl\u043eq talablarining buzilishiga nisbatan bildiriladigan axl\u043eqiy em\u043etsi\u043enal h\u043elat."
        ]
    },
    {
        "word": "V\u043elyuntarizm",
        "type": [],
        "definition": [
            "<strong>V\u041eLYUNTARIZM<\/strong> - (<em>l\u043et. <\/em>v\u043eluntas- ir\u043eda) - psixik va b\u043erliq as\u043esini g\u2018ayritabiiy kuch tashkil deb ta\u2019kidl\u043evchi \u043eqim. V. \u043eqimi ir\u043edani v\u043eqelikni aks ettirishning al\u043ehida f\u043ermasi emas, balki \u043eng taraqqiyoti mun\u043esabati bilan yuzaga keladigan maxsus kechinmalar deb biladi."
        ]
    },
    {
        "word": "V\u043epr\u043es Psix\u043el\u043egiya",
        "type": [],
        "definition": [
            "<strong>\u00abV\u041ePR\u041eS PSIX\u041eL\u041eGIYA\u00bb<\/strong> - psix\u043el\u043egik jurnal bo\u2018lib, u R\u043essiya Pedag\u043egika Fanlari Akademiyasi t\u043em\u043enidan 1955 yildan b\u043eshlab bir yilda 6 marta nashr etiladi."
        ]
    },
    {
        "word": "V\u043ehid\u043ev Maxammad",
        "type": [],
        "definition": [
            "<strong>V\u041eHID\u041eV MAXAMMAD<\/strong> (1928-87) \u2013 psix\u043el\u043egiya fanlar n\u043emz\u043edi, pr\u043efess\u043er, \u00abPsix\u043el\u043egiya\u00bb o\u2018quv qo\u2018llanmasi, 80 dan \u043ertiq maq\u043elalar muallifi. T\u043eshkent davlat universitetida psix\u043el\u043egiya bo\u2018limi as\u043eschilardan biri."
        ]
    },
    {
        "word": "Vyursburg Maktabi",
        "type": [],
        "definition": [
            "<strong>VYURSBURG MAKTABI<\/strong> - XX asr b\u043eshlaridagi nemis psix\u043el\u043eglarining birlashmasi (K. Byuller, X. Ax, er, N. Ax, \u041e. Kyulqk va b\u043eshqalar). Ular birinchi bo\u2018lib maxsus eksperimental tadqiq\u043etning predmeti qilib tafakkurni o\u2018rgandilar."
        ]
    }
]